statsmaker/__init__.py
statsmaker/statsmaker_base.py
statsmaker-1.0.0.dist-info/LICENSE
statsmaker-1.0.0.dist-info/METADATA
statsmaker-1.0.0.dist-info/WHEEL
statsmaker-1.0.0.dist-info/top_level.txt
statsmaker-1.0.0.dist-info/RECORD
