Metadata-Version: 2.1
Name: statsmaker
Version: 1.0.0
Summary: Probabilistic Progamming Language (PPL) for Market Microstructure Modeling
Home-page: https://github.com/jialuechen/statsmaker
Author: Jialue Chen
Author-email: jialuechen@outlook.com
License: Apache-2.0
Requires-Python: >=3.6
License-File: LICENSE
Requires-Dist: pyro-ppl
Requires-Dist: torch
